{
"type": "FeatureCollection",
"features": [
{ "type": "Feature", "properties": { "agency_cd": "USGS", "site_no": "01049265", "station_nm": "Kennebec River at North Sidney, Maine", "site_tp_cd": "ST", "lat_va": 442820.0, "long_va": 694102.0, "coord_meth_cd": "N", "coord_acy_cd": "S", "coord_datum_cd": "NAD83", "dec_coord_datum_cd": "NAD83", "district_cd": "23", "state_cd": "23", "county_cd": "011", "country_cd": "US", "land_net_ds": null, "map_nm": "Vassalboro", "map_scale_fc": "  24000", "alt_va": 15.12, "alt_meth_cd": "L", "alt_acy_va": 0.01, "alt_datum_cd": "NGVD29", "huc_cd": "01030003", "basin_cd": null, "topo_cd": null, "instruments_cd": "YNNNYNNNNYNNNNNNNNNNNNNNNNNNNN", "construction_dt": null, "inventory_dt": null, "drain_area_va": 5403.0, "contrib_drain_area_va": 5403.0, "tz_cd": "EST", "local_time_fg": "Y", "reliability_cd": null, "gw_file_cd": "NNNNNNNN", "nat_aqfr_cd": null, "aqfr_cd": null, "aqfr_type_cd": null, "well_depth_va": null, "hole_depth_va": null, "depth_src_cd": null, "project_no": "442300100" }, "geometry": { "type": "Point", "coordinates": [ -69.6838889, 44.4722222 ] } }
]
}
