{
"type": "FeatureCollection",
"features": [
{ "type": "Feature", "properties": { "agency_cd": "USGS", "site_no": "02465000", "station_nm": "BLACK WARRIOR RIVER AT NORTHPORT AL", "site_tp_cd": "ST", "lat_va": 331233.0, "long_va": 873524.0, "coord_meth_cd": "M", "coord_acy_cd": "U", "coord_datum_cd": "NAD27", "dec_coord_datum_cd": "NAD83", "district_cd": "01", "state_cd": "01", "county_cd": "125", "country_cd": "US", "land_net_ds": null, "map_nm": null, "map_scale_fc": null, "alt_va": 0.0, "alt_meth_cd": "U", "alt_acy_va": 0.01, "alt_datum_cd": "NGVD29", "huc_cd": "03160112", "basin_cd": null, "topo_cd": null, "instruments_cd": "YNNNYNNNNNNNNNNNNNNNNNNNNNNNNN", "construction_dt": null, "inventory_dt": null, "drain_area_va": 4820.0, "contrib_drain_area_va": 4820.0, "tz_cd": "CST", "local_time_fg": "Y", "reliability_cd": null, "gw_file_cd": "NNNNNNNN", "nat_aqfr_cd": null, "aqfr_cd": null, "aqfr_type_cd": null, "well_depth_va": null, "hole_depth_va": null, "depth_src_cd": null, "project_no": null }, "geometry": { "type": "Point", "coordinates": [ -87.5900074, 33.2092853 ] } }
]
}
