{
"type": "FeatureCollection",
"features": [
{ "type": "Feature", "properties": { "agency_cd": "USGS", "site_no": "09163500", "station_nm": "COLORADO RIVER NEAR COLORADO-UTAH STATE LINE", "site_tp_cd": "ST", "lat_va": 390758.0, "long_va": 1090135.0, "coord_meth_cd": "M", "coord_acy_cd": "S", "coord_datum_cd": "NAD27", "dec_coord_datum_cd": "NAD83", "district_cd": "08", "state_cd": "08", "county_cd": "077", "country_cd": "US", "land_net_ds": "  SENWS05 T011S R104W", "map_nm": "BITTER CREEK WELL,CO", "map_scale_fc": "  24000", "alt_va": 4325.0, "alt_meth_cd": "M", "alt_acy_va": 20.0, "alt_datum_cd": "NGVD29", "huc_cd": "14010005", "basin_cd": null, "topo_cd": null, "instruments_cd": "NNNNYNYNNNNNNNNNNNNNNNNNNNNNNN", "construction_dt": null, "inventory_dt": null, "drain_area_va": 17849.0, "contrib_drain_area_va": null, "tz_cd": "MST", "local_time_fg": "Y", "reliability_cd": null, "gw_file_cd": "NYNNNNNN", "nat_aqfr_cd": null, "aqfr_cd": null, "aqfr_type_cd": null, "well_depth_va": null, "hole_depth_va": null, "depth_src_cd": null, "project_no": "460800110" }, "geometry": { "type": "Point", "coordinates": [ -109.0270546, 39.1327605 ] } }
]
}
